req_enc_dec/__init__.py
req_enc_dec/middleware.py
req_enc_dec/req_crypto.py
req_enc_dec-0.2.1.dist-info/METADATA
req_enc_dec-0.2.1.dist-info/WHEEL
req_enc_dec-0.2.1.dist-info/top_level.txt
req_enc_dec-0.2.1.dist-info/RECORD
