Metadata-Version: 2.1
Name: req-enc-dec
Version: 0.2.1
Summary: Request/Response Encryption/Decryption Middleware
Home-page: https://github.com/Michaelxwb/ReqEncDec
Author: Jahan
Author-email: ambition_xu@163.com
License: MIT
Keywords: middleware encryption decryption
Platform: UNKNOWN
Requires-Dist: pycryptodome>=3.10.1
